{
  "totalEtfs": 5269,
  "processed": 5269,
  "succeeded": 5241,
  "failed": 28,
  "lastProcessedTicker": "ZZZ",
  "failedTickers": [
    "ATCL",
    "AXPG",
    "CGBLF",
    "EFMSF",
    "FCXG",
    "GSUI",
    "HMLSF",
    "HNUZF",
    "IHRMF",
    "IHSFF",
    "IHSXF",
    "ISRPF",
    "IUNSF",
    "IVSX",
    "JREM",
    "NTETF",
    "SKK",
    "SMRF",
    "SMZ",
    "SUIS",
    "VHYD",
    "VNGDF",
    "WDCX",
    "XDEF",
    "XKFS",
    "XKII",
    "XKST",
    "ZKBGF"
  ],
  "startedAt": "2026-02-21T20:54:51.103Z",
  "lastUpdatedAt": "2026-02-21T23:06:31.159Z"
}